fsm_agent/__init__.py
fsm_agent/fsm.py
fsm_agent/tool_registry.py
fsm_agent/utils.py
fsm_agent_fw-0.1.0.dist-info/METADATA
fsm_agent_fw-0.1.0.dist-info/WHEEL
fsm_agent_fw-0.1.0.dist-info/licenses/LICENSE
fsm_agent_fw-0.1.0.dist-info/RECORD
