Metadata-Version: 2.4
Name: fsm-agent-fw
Version: 0.1.0
Summary: A Finite State Machine (FSM) driven agent framework for reliable and structured LLM interactions.
Author: shuent
License: MIT
License-File: LICENSE
Classifier: License :: OSI Approved :: MIT License
Classifier: Operating System :: OS Independent
Classifier: Programming Language :: Python :: 3
Requires-Python: >=3.13
Requires-Dist: google-genai>=1.61.0
Requires-Dist: python-dotenv>=1.2.1
